json_kit/__init__.py
json_kit/_constants.py
json_kit/encoder/AllRefJSONEncoder.py
json_kit/encoder/RefJSONEncoder.py
json_kit/encoder/SimpleJSONEncoder.py
json_kit/encoder/__init__.py
json_kit/encoder/utils.py
json_kit/loader/__init__.py
json_kit/loader/load_json_file.py
json_kit-1.0.8.dist-info/METADATA
json_kit-1.0.8.dist-info/WHEEL
json_kit-1.0.8.dist-info/top_level.txt
json_kit-1.0.8.dist-info/RECORD
