Metadata-Version: 2.1
Name: json-kit
Version: 1.0.8
Summary: UNKNOWN
Home-page: https://github.com/fortfall/json_kit
Author: lihailin
License: MIT
Platform: UNKNOWN
Classifier: Programming Language :: Python :: 3
Classifier: License :: OSI Approved :: MIT License
Classifier: Operating System :: OS Independent
Requires-Python: >=3.5
Requires-Dist: chardet
